bright_horizons_backup/__init__.py
bright_horizons_backup/api_client.py
bright_horizons_backup/auth.py
bright_horizons_backup/browser_utils.py
bright_horizons_backup/cli.py
bright_horizons_backup/client.py
bright_horizons_backup/constants.py
bright_horizons_backup/models.py
bright_horizons_backup/utils.py
bright_horizons_backup/viewer.py
bright_horizons_backup/templates/base.html
bright_horizons_backup/templates/gallery.html
bright_horizons_backup/templates/index.html
bright_horizons_backup/templates/month_reports.html
bright_horizons_backup/templates/months.html
bright_horizons_backup/templates/report_detail.html
bright_horizons_backup/templates/reports.html
bright_horizons_backup-1.0.0.dist-info/licenses/LICENSE
bright_horizons_backup-1.0.0.dist-info/METADATA
bright_horizons_backup-1.0.0.dist-info/WHEEL
bright_horizons_backup-1.0.0.dist-info/entry_points.txt
bright_horizons_backup-1.0.0.dist-info/top_level.txt
bright_horizons_backup-1.0.0.dist-info/RECORD
