Metadata-Version: 2.4
Name: bright-horizons-backup
Version: 1.0.0
Summary: A Python client for backing up daily reports and photos from Bright Horizons daycare centers
Author-email: Hadrien Glaude <hadrien.glaude@gmail.com>
Maintainer-email: Hadrien Glaude <hadrien.glaude@gmail.com>
License: MIT
Project-URL: Homepage, https://github.com/marsuleouf/bright-horizons-backup
Project-URL: Repository, https://github.com/marsuleouf/bright-horizons-backup
Project-URL: Issues, https://github.com/marsuleouf/bright-horizons-backup/issues
Project-URL: Changelog, https://github.com/marsuleouf/bright-horizons-backup/blob/main/CHANGELOG.md
Keywords: bright-horizons,daycare,backup,scraping,childcare
Classifier: Development Status :: 4 - Beta
Classifier: Intended Audience :: End Users/Desktop
Classifier: License :: OSI Approved :: MIT License
Classifier: Operating System :: OS Independent
Classifier: Programming Language :: Python :: 3
Classifier: Programming Language :: Python :: 3.8
Classifier: Programming Language :: Python :: 3.9
Classifier: Programming Language :: Python :: 3.10
Classifier: Programming Language :: Python :: 3.11
Classifier: Programming Language :: Python :: 3.12
Classifier: Topic :: Internet :: WWW/HTTP :: Browsers
Classifier: Topic :: System :: Archiving :: Backup
Classifier: Topic :: Utilities
Requires-Python: >=3.8.1
License-File: LICENSE
Requires-Dist: playwright>=1.40.0
Requires-Dist: httpx>=0.25.0
Requires-Dist: pydantic>=2.0.0
Requires-Dist: python-dotenv>=1.0.0
Provides-Extra: viewer
Requires-Dist: flask>=2.0.0; extra == "viewer"
Provides-Extra: test
Requires-Dist: pytest>=7.0.0; extra == "test"
Requires-Dist: pytest-asyncio>=0.21.0; extra == "test"
Requires-Dist: pytest-mock>=3.10.0; extra == "test"
Requires-Dist: pytest-cov>=4.0.0; extra == "test"
Provides-Extra: dev
Requires-Dist: pytest>=7.0.0; extra == "dev"
Requires-Dist: pytest-asyncio>=0.21.0; extra == "dev"
Requires-Dist: pytest-mock>=3.10.0; extra == "dev"
Requires-Dist: pytest-cov>=4.0.0; extra == "dev"
Requires-Dist: black>=23.0.0; extra == "dev"
Requires-Dist: isort>=5.12.0; extra == "dev"
Requires-Dist: flake8>=6.0.0; extra == "dev"
Requires-Dist: mypy>=1.0.0; extra == "dev"
Requires-Dist: tox>=4.0.0; extra == "dev"
Requires-Dist: build>=0.10.0; extra == "dev"
Requires-Dist: twine>=4.0.0; extra == "dev"
Requires-Dist: pre-commit>=3.0.0; extra == "dev"
Requires-Dist: bandit>=1.7.0; extra == "dev"
Requires-Dist: safety>=3.0.0; extra == "dev"
Dynamic: license-file
